converter_gokuln/__init__.py
converter_gokuln/lenconv.py
converter_gokuln/massconv.py
converter_gokuln/tempconv.py
converter_gokuln-0.0.2.dist-info/License.txt
converter_gokuln-0.0.2.dist-info/METADATA
converter_gokuln-0.0.2.dist-info/WHEEL
converter_gokuln-0.0.2.dist-info/top_level.txt
converter_gokuln-0.0.2.dist-info/RECORD
