Metadata-Version: 2.1
Name: converter-gokuln
Version: 0.0.2
Summary: A small example package
Author-email: Gokul nath C S <csgokulhpd@gmail.com>
Project-URL: Homepage, https://github.com/pypa/sampleproject
Project-URL: Bug Tracker, https://github.com/pypa/sampleproject/issues
Classifier: Programming Language :: Python :: 3
Classifier: License :: OSI Approved :: MIT License
Classifier: Operating System :: OS Independent
Requires-Python: >=3.7
License-File: License.txt
